app/__init__.py
app/index.py
app/Screens/__init__.py
app/Screens/About/__init__.py
app/Screens/About/main.py
app/Screens/Home/__init__.py
app/Screens/Home/main.py
pyreact/__init__.py
pyreact/cli.py
pyreact/dom.py
pyreact/emitter.py
pyreact/helper.py
pyreact/htmlparser.py
pyreact/main.py
pyreact/responses.py
pyreact/state.py
pyreact/stylesheet.py
pyreact/tools.py
pyreact/version.py
pyreact/data/App.css
pyreact/data/App.py
pyreact/data/README.md
pyreact/data/index.html
pyreact/data/index.py
pyreact/data/manifest.json
pyreact2-0.0.4.data/data/data_files/App.css
pyreact2-0.0.4.data/data/data_files/App.py
pyreact2-0.0.4.data/data/data_files/README.md
pyreact2-0.0.4.data/data/data_files/index.html
pyreact2-0.0.4.data/data/data_files/index.py
pyreact2-0.0.4.data/data/data_files/manifest.json
pyreact2-0.0.4.dist-info/METADATA
pyreact2-0.0.4.dist-info/WHEEL
pyreact2-0.0.4.dist-info/entry_points.txt
pyreact2-0.0.4.dist-info/top_level.txt
pyreact2-0.0.4.dist-info/RECORD
