Metadata-Version: 2.1
Name: pyreact2
Version: 0.0.4
Summary: A pythonic adaptation of React JS
Home-page: https://github.com/ableinc/pyreact
Author: Jaylen A. Douglas | Able Inc.
Author-email: douglas.jaylen@gmail.com
License: ISC
Keywords: react js,web development,client side,server side,able inc,jaylen douglas,python 3.6,browser,UI,python javascript,html,python 3,css,html
Platform: UNKNOWN
Classifier: Programming Language :: Python :: 3
Classifier: License :: OSI Approved :: MIT License
Classifier: Operating System :: OS Independent
Requires-Dist: sanic (==20.6.3)
Requires-Dist: pydotenvs (==0.1.4)
Requires-Dist: beautifulsoup4 (==4.9.1)
Requires-Dist: pipreqs (==0.4.10)
Requires-Dist: Click (==7.0)
